pyfilemail/__init__.py
pyfilemail/__main__.py
pyfilemail/errors.py
pyfilemail/transfer.py
pyfilemail/urls.py
pyfilemail/users.py
pyfilemail-0.5.1.dist-info/DESCRIPTION.rst
pyfilemail-0.5.1.dist-info/METADATA
pyfilemail-0.5.1.dist-info/RECORD
pyfilemail-0.5.1.dist-info/WHEEL
pyfilemail-0.5.1.dist-info/entry_points.txt
pyfilemail-0.5.1.dist-info/metadata.json
pyfilemail-0.5.1.dist-info/top_level.txt
