Metadata-Version: 2.0
Name: pyfilemail
Version: 0.5.1
Summary: Python command line tool and API for file transfers with www.filemail.com
Home-page: https://github.com/apetrynet/pyfilemail
Author: Daniel Flehner Heen
Author-email: UNKNOWN
License: MIT
Download-URL: https://github.com/apetrynet/pyfilemail/tarball/0.5.1
Keywords: filemail,pyfilemail,file transfer,large file transfer,fast transfer,transfer,fast
Platform: UNKNOWN
Classifier: Development Status :: 4 - Beta
Classifier: Intended Audience :: Developers
Classifier: Natural Language :: English
Classifier: License :: OSI Approved :: MIT License
Classifier: Programming Language :: Python
Classifier: Programming Language :: Python :: 2.6
Classifier: Programming Language :: Python :: 2.7
Requires-Dist: requests
Requires-Dist: requests-toolbelt
Requires-Dist: appdirs
Requires-Dist: keyring
Requires-Dist: clint
